MANIFEST.in
README.rst
setup.py
pybb/__init__.py
pybb/admin.py
pybb/context_processors.py
pybb/defaults.py
pybb/feeds.py
pybb/forms.py
pybb/middleware.py
pybb/models.py
pybb/signals.py
pybb/subscription.py
pybb/tests.py
pybb/urls.py
pybb/util.py
pybb/views.py
pybb/management/__init__.py
pybb/management/commands/__init__.py
pybb/management/commands/dump_topics.py
pybb/management/commands/migrate_profile.py
pybb/management/commands/pybb_delete_invalid_topics.py
pybb/management/commands/pybb_update_counters.py
pybb/management/commands/supermoderator.py
pybb/migrations/0001_initial.py
pybb/migrations/0002_remove_avatar.py
pybb/migrations/0003_missing_columns.py
pybb/migrations/0004_fixit.py
pybb/migrations/0005_ToAuto.py
pybb/migrations/0006_autoone.py
pybb/migrations/0007_addavatar.py
pybb/migrations/0008_newreadtracking.py
pybb/migrations/0009_remove_last_post.py
pybb/migrations/0010_addhiddenoption.py
pybb/migrations/0011_adddefaultpermissions.py
pybb/migrations/0012_permission_adding.py
pybb/migrations/0013_abstract_profile.py
pybb/migrations/0014_add_topic_headline.py
pybb/migrations/0015_autosubscribe.py
pybb/migrations/0016_auto__del_field_post_markup__del_field_profile_markup.py
pybb/migrations/0017_add_pre_moderation.py
pybb/migrations/0018_add_file_attachment.py
pybb/migrations/0019_remove_attachment_fields.py
pybb/migrations/__init__.py
pybb/static/pybb.css
pybb/static/pybb_bootstrap.css
pybb/static/pybb_bootstrap.less
pybb/static/markitup/ajax_csrf.js
pybb/static/markitup/jquery.markitup.js
pybb/static/markitup/preview.css
pybb/static/markitup/sets/bbcode/readme.txt
pybb/static/markitup/sets/bbcode/set.js
pybb/static/markitup/sets/bbcode/style.css
pybb/static/markitup/sets/bbcode/images/bold.png
pybb/static/markitup/sets/bbcode/images/clean.png
pybb/static/markitup/sets/bbcode/images/code.png
pybb/static/markitup/sets/bbcode/images/fonts.png
pybb/static/markitup/sets/bbcode/images/italic.png
pybb/static/markitup/sets/bbcode/images/link.png
pybbm_tbw.egg-info/PKG-INFO
pybbm_tbw.egg-info/SOURCES.txt
pybbm_tbw.egg-info/dependency_links.txt
pybbm_tbw.egg-info/requires.txt
pybbm_tbw.egg-info/top_level.txt