Metadata-Version: 1.0
Name: pybbm-tbw
Version: 0.8.0-7
Summary: PyBB Modified, Modified. Django forum application modified to work with other languages than Russian and English, as well as working with easy_thumbnails
Home-page: UNKNOWN
Author: Trygve Bertelsen Wiig
Author-email: trygvebw@gmail.com
License: BSD
Keywords: django application forum board
Platform: UNKNOWN
Classifier: Development Status :: 4 - Beta
Classifier: Environment :: Web Environment
Classifier: Framework :: Django
Classifier: Intended Audience :: Developers
Classifier: License :: OSI Approved :: BSD License
Classifier: Operating System :: OS Independent
Classifier: Programming Language :: Python
Classifier: Topic :: Internet :: WWW/HTTP :: Dynamic Content :: Message Boards
Classifier: Topic :: Software Development :: Libraries :: Python Modules
